{
  "swagger": "2.0",
  "info": {
    "title": "Budget Buddy API",
    "version": "1.0.0"
  },
  "schemes": ["http"],
  "basePath": "/api/v1",
  "consumes": ["application/json"],
  "produces": ["application/json"],
  "paths": {
    "/expense": {
      "get": {
        "summary": "GET /expense",
        "operationId": "GetExpenses",
        "responses": {
          "200": {
            "description": "List all expenses",
            "schema": {
              "$ref": "#/definitions/expenseListResponse"
            }
          },
          "500": {
            "description": "Error response",
            "schema": {
              "$ref": "#/definitions/generalErrorResponse"
            }
          }
        },
        "tags": ["Expenses"]
      },
      "post": {
        "summary": "GET /expense",
        "operationId": "PostExpenses",
        "parameters": [
          {
            "name": "Body",
            "in": "body",
            "description": "Expense request body",
            "schema": {
              "$ref": "#/definitions/expensePostBody"
            }
          }
        ],
        "responses": {},
        "tags": ["Expenses"]
      }
    }
  },
  "definitions": {
    "expenseListResponse": {
      "type": "object",
      "properties": {
        "data": {
          "type": "array",
          "items": {
            "$ref": "#/definitions/expenseItem"
          }
        }
      }
    },
    "expenseItem": {
      "type": "object",
      "properties": {
        "expense_id": {
          "type": "integer"
        },
        "name": {
          "type": "string"
        }
      }
    },
    "expensePostBody": {
      "type": "object",
      "properties": {
        "name": {
          "type": "string"
        }
      }
    },
    "generalErrorResponse": {
      "type": "object",
      "properties": {
        "error": {
          "type": "object",
          "properties": {
            "code": {
              "type": "integer"
            },
            "message": {
              "type": "string"
            }
          }
        }
      }
    }
  }
}
